{"name":"Astar","shortName":"ASTR","logo":"https://s2.coinmarketcap.com/static/img/coins/64x64/12885.png","ecosystem":"Polkadot","blockExplorer":"https://astar.subscan.io/","jsonRPC":"https://astar.public.blastapi.io","url":"https://astar.network/","description":"Astar is a scalable decentralized blockchain for the next big Web3 innovations.","category":[],"tags":[],"value":0.051328964284058094,"valueUpdated":"2023-05-13T00:34:00.000Z","blockNumber":3555113,"blockNumberUpdated":"2023-05-13T00:35:18.000Z"}